[
  {
    "ano": 2022,
    "ordinal": 3,
    "tipo": "pdf",
    "cuc": false,
    "natureza": "espera",
    "arquivo": "2022_e3.txt"
  },
  {
    "ano": 2022,
    "ordinal": 2,
    "tipo": "pdf",
    "cuc": false,
    "natureza": "espera",
    "arquivo": "2022_e2.txt"
  },
  {
    "ano": 2022,
    "ordinal": 1,
    "tipo": "pdf",
    "cuc": false,
    "natureza": "espera",
    "arquivo": "2022_e1.txt"
  },
  {
    "ano": 2022,
    "ordinal": 3,
    "tipo": "pdf",
    "cuc": false,
    "natureza": "chamada",
    "arquivo": "2022_3.txt"
  },
  {
    "ano": 2022,
    "ordinal": 2,
    "tipo": "pdf",
    "cuc": false,
    "natureza": "chamada",
    "arquivo": "2022_2.txt"
  },
  {
    "ano": 2022,
    "ordinal": 1,
    "tipo": "pdf",
    "cuc": false,
    "natureza": "chamada",
    "arquivo": "2022_1.txt"
  },
  {
    "ano": 2021,
    "ordinal": 3,
    "tipo": "pdf",
    "cuc": false,
    "natureza": "espera",
    "arquivo": "2021_e3.txt"
  },
  {
    "ano": 2021,
    "ordinal": 2,
    "tipo": "pdf",
    "cuc": false,
    "natureza": "espera",
    "arquivo": "2021_e2.txt"
  },
  {
    "ano": 2021,
    "ordinal": 1,
    "tipo": "pdf",
    "cuc": false,
    "natureza": "espera",
    "arquivo": "2021_e1.txt"
  },
  {
    "ano": 2021,
    "ordinal": 3,
    "tipo": "pdf",
    "cuc": true,
    "natureza": "chamada",
    "arquivo": "2021_3.txt"
  },
  {
    "ano": 2021,
    "ordinal": 2,
    "tipo": "pdf",
    "cuc": true,
    "natureza": "chamada",
    "arquivo": "2021_2.txt"
  },
  {
    "ano": 2021,
    "ordinal": 1,
    "tipo": "pdf",
    "cuc": true,
    "natureza": "chamada",
    "arquivo": "2021_1.txt"
  },
  {
    "ano": 2020,
    "ordinal": 3,
    "tipo": "pdf",
    "cuc": true,
		"natureza": "chamada",
    "arquivo": "2020_3.txt"
  },
  {
    "ano": 2020,
    "ordinal": 2,
    "tipo": "pdf",
    "cuc": true,
		"natureza": "chamada",
    "arquivo": "2020_2.txt"
  },
  {
    "ano": 2020,
    "ordinal": 1,
    "tipo": "pdf",
    "cuc": true,
		"natureza": "chamada",
    "arquivo": "2020_1.txt"
  },
  {
    "ano": 2019,
    "ordinal": 4,
    "tipo": "pdf",
    "cuc": true,
		"natureza": "lista de espera",
    "arquivo": "2019_e4.txt"
  },
  {
    "ano": 2019,
    "ordinal": 3,
    "tipo": "pdf",
    "cuc": true,
		"natureza": "lista de espera",
    "arquivo": "2019_e3.txt"
  },
  {
    "ano": 2019,
    "ordinal": 2,
    "tipo": "pdf",
    "cuc": true,
		"natureza": "lista de espera",
    "arquivo": "2019_e2.txt"
  },
  {
    "ano": 2019,
    "ordinal": 1,
    "tipo": "pdf",
    "cuc": true,
		"natureza": "lista de espera",
    "arquivo": "2019_e1.txt"
  },
  {
    "ano": 2019,
    "ordinal": 5,
    "tipo": "pdf",
    "cuc": true,
		"natureza": "chamada",
    "arquivo": "2019_5.txt"
  },
  {
    "ano": 2019,
    "ordinal": 4,
    "tipo": "pdf",
    "cuc": true,
		"natureza": "chamada",
    "arquivo": "2019_4.txt"
  },
  {
    "ano": 2019,
    "ordinal": 3,
    "tipo": "pdf",
    "cuc": true,
		"natureza": "chamada",
    "arquivo": "2019_3.txt"
  },
  {
    "ano": 2019,
    "ordinal": 2,
    "tipo": "pdf",
    "cuc": true,
		"natureza": "chamada",
    "arquivo": "2019_2.txt"
  },
  {
    "ano": 2019,
    "ordinal": 1,
    "tipo": "pdf",
    "cuc": true,
		"natureza": "chamada",
    "arquivo": "2019_1.txt"
  },
  {
    "ano": 2018,
    "ordinal": 8,
		"tipo": "pdf",
    "cuc": false,
		"natureza": "chamada",
    "arquivo": "2018_8.txt"
  },
  {
    "ano": 2018,
    "ordinal": 7,
    "tipo": "pdf",
    "cuc": false,
		"natureza": "chamada",
    "arquivo": "2018_7.txt"
  },
  {
    "ano": 2018,
    "ordinal": 6,
    "tipo": "pdf",
    "cuc": false,
		"natureza": "chamada",
    "arquivo": "2018_6.txt"
  },
  {
    "ano": 2018,
    "ordinal": 5,
    "tipo": "pdf",
    "cuc": false,
		"natureza": "chamada",
    "arquivo": "2018_5.txt"
  },
  {
    "ano": 2018,
    "ordinal": 4,
    "tipo": "pdf",
    "cuc": false,
		"natureza": "chamada",
    "arquivo": "2018_4.txt"
  },
  {
    "ano": 2018,
    "ordinal": 3,
    "tipo": "pdf",
    "cuc": false,
		"natureza": "chamada",
    "arquivo": "2018_3.txt"
  },
  {
    "ano": 2018,
    "ordinal": 2,
    "tipo": "pdf",
    "cuc": false,
		"natureza": "chamada",
    "arquivo": "2018_2.txt"
  },
  {
    "ano": 2018,
    "ordinal": 1,
    "tipo": "pdf",
    "cuc": false,
		"natureza": "chamada",
    "arquivo": "2018_1.txt"
  }
]
